cologging/__init__.py
cologging-0.1.dist-info/LICENSE
cologging-0.1.dist-info/METADATA
cologging-0.1.dist-info/WHEEL
cologging-0.1.dist-info/top_level.txt
cologging-0.1.dist-info/RECORD
