Metadata-Version: 2.1
Name: cologging
Version: 0.1
Summary: ColorFormatter class for logging module.
Home-page: https://github.com/filwie/cologging
Author: Filip Wiechec
Author-email: filip.wiechec@gmail.com
License: MIT
Keywords: logging color
Platform: UNKNOWN
Classifier: Programming Language :: Python :: 3
Classifier: License :: OSI Approved :: MIT License
Requires-Dist: incolor
